cosmic_datapi/__init__.py
cosmic_datapi/api/__init__.py
cosmic_datapi/api/actions.py
cosmic_datapi/api/models.py
cosmic_datapi/builders/__init__.py
cosmic_datapi/builders/block.py
cosmic_datapi/builders/block_events.py
cosmic_datapi/builders/block_state.py
cosmic_datapi/builders/block_state_generator.py
cosmic_datapi/builders/model.py
cosmic_datapi-0.0.10.dist-info/METADATA
cosmic_datapi-0.0.10.dist-info/WHEEL
cosmic_datapi-0.0.10.dist-info/RECORD
