Metadata-Version: 2.3
Name: cosmic-datapi
Version: 0.0.10
Summary: Basically a library to create data mods in Cosmic Reach really fast.
Project-URL: Homepage, https://codeberg.org/EmmaTheMartian/cosmic-datapi
Project-URL: Issues, https://codeberg.org/EmmaTheMartian/cosmic-datapi/issues
Author-email: EmmaTheMartian <emmathemartian@gmail.com>
Classifier: License :: OSI Approved :: MIT License
Classifier: Programming Language :: Python :: 3
Requires-Python: >=3.10
Requires-Dist: tqdm
